mplogp/__init__.py
mplogp/mplogp.py
mplogp-0.1.1.dist-info/METADATA
mplogp-0.1.1.dist-info/WHEEL
mplogp-0.1.1.dist-info/entry_points.txt
mplogp-0.1.1.dist-info/namespace_packages.txt
mplogp-0.1.1.dist-info/top_level.txt
mplogp-0.1.1.dist-info/zip-safe
mplogp-0.1.1.dist-info/RECORD
